redistypes/__init__.py
redistypes/bindings.py
redistypes/descriptors.py
redistypes-0.2.0.dist-info/LICENSE
redistypes-0.2.0.dist-info/METADATA
redistypes-0.2.0.dist-info/WHEEL
redistypes-0.2.0.dist-info/top_level.txt
redistypes-0.2.0.dist-info/RECORD
