Metadata-Version: 2.1
Name: redistypes
Version: 0.2.0
Summary: Redis native types for Python
Home-page: https://github.com/vladimirshkoda/redis-bindings
Author: Vladimir Shkoda
Author-email: vladimir.shkoda.51@gmail.com
License: MIT
Keywords: redis,key-value,store,bindings,types,descriptor,orm
Platform: any
Classifier: Development Status :: 3 - Alpha
Classifier: Environment :: Plugins
Classifier: Intended Audience :: Developers
Classifier: License :: OSI Approved :: MIT License
Classifier: Programming Language :: Python
Classifier: Topic :: Database
Classifier: Topic :: Software Development
Requires-Python: >=3.5
Requires-Dist: redis (>=3.0)
